skyter/__init__.py
skyter/app.py
skyter/bsky.py
skyter/data_classes.py
skyter/login.py
skyter/main_screen.py
skyter/profile.py
skyter/search.py
skyter/settings.py
skyter/styles.tcss
skyter/ui.py
skyter/user_actions.py
skyter/utils.py
skyter/compose/compose.py
skyter/compose/link.py
skyter/compose/media.py
skyter/compose/post_compose.py
skyter/feeds/container.py
skyter/feeds/custom_feeds.py
skyter/feeds/feed.py
skyter/feeds/notifications.py
skyter/feeds/posts.py
skyter/feeds/starter_packs.py
skyter/feeds/thread.py
skyter/feeds/users.py
skyter-0.1.3.dist-info/METADATA
skyter-0.1.3.dist-info/WHEEL
skyter-0.1.3.dist-info/entry_points.txt
skyter-0.1.3.dist-info/top_level.txt
skyter-0.1.3.dist-info/RECORD
