Metadata-Version: 2.4
Name: skyter
Version: 0.1.3
Summary: TUI for Bsky
Author-email: Hudson Bailey <dev@hudsonbailey.org>
License: MIT License
Project-URL: Homepage, https://github.com/hdb/skyter
Project-URL: Bug Tracker, https://github.com/hdb/skyter/issues
Project-URL: Documentation, https://skyter.readthedocs.io
Keywords: atproto,bsky,bluesky,textual,tui
Classifier: Programming Language :: Python :: 3
Classifier: License :: OSI Approved :: MIT License
Classifier: Operating System :: OS Independent
Classifier: Topic :: Communications
Requires-Python: >=3.8
Requires-Dist: atproto>=0.0.61
Requires-Dist: pyperclip>=1.9.0
Requires-Dist: textual>=5.2.0
Requires-Dist: pyfiglet>=1.0.3
Requires-Dist: textual-fspicker>=0.4.1
Requires-Dist: beautifulsoup4>=4.13.4
Requires-Dist: aiohttp>=3.12.13
